AUTHORS.rst
CHANGELOG.rst
LICENSE
MANIFEST.in
README.rst
setup.py
django_pummel.egg-info/PKG-INFO
django_pummel.egg-info/SOURCES.txt
django_pummel.egg-info/dependency_links.txt
django_pummel.egg-info/not-zip-safe
django_pummel.egg-info/requires.txt
django_pummel.egg-info/top_level.txt
pml/__init__.py
pml/constants.py
pml/middleware.py
pml/models.py
pml/test_urls.py
pml/test_view.py
pml/tests.py
pml/utils.py
pml/forms/__init__.py
pml/forms/fields.py
pml/forms/widgets.py
pml/static/pml/banner.png
pml/static/pml/icon.jpg
pml/static/pml/icon.png
pml/templates/pml/base.xml
pml/templates/pml/base_image_container.xml
pml/templates/pml/base_module.xml
pml/templates/pml/form.xml
pml/templates/pml/image_link_text.xml
pml/templates/pml/image_tag.xml
pml/templates/pml/image_text_link.xml
pml/templates/pml/label_tag.xml
pml/templates/pml/redirect.xml
pml/templates/pml/inclusion_tags/banner.xml
pml/templates/pml/inclusion_tags/clickable_banner.xml
pml/templates/pml/inclusion_tags/divider.xml
pml/templates/pml/inclusion_tags/form.xml
pml/templates/pml/inclusion_tags/header.xml
pml/templates/pml/inclusion_tags/link_tag.xml
pml/templates/pml/inclusion_tags/list.xml
pml/templates/pml/inclusion_tags/page_banner.xml
pml/templates/pml/inclusion_tags/redirect.xml
pml/templates/pml/inclusion_tags/text_module.xml
pml/templates/pml/inclusion_tags/text_tag.xml
pml/templates/pml/inclusion_tags/thumbnail_html.xml
pml/templates/pml/inclusion_tags/title_tag.xml
pml/templates/pml/tests/banner.html
pml/templates/pml/tests/download_inline_block.html
pml/templates/pml/tests/home.html
pml/templates/pml/tests/modelbase_block_include.html
pml/templates/pml/tests/object_detail_header_include.html
pml/templates/pml/tests/promo_block_include.html
pml/templates/pml/widgets/choice.xml
pml/templates/pml/widgets/hidden.xml
pml/templates/pml/widgets/select.xml
pml/templates/pml/widgets/text.xml
pml/templatetags/__init__.py
pml/templatetags/__init__.pyc
pml/templatetags/pml_inclusion_tags.py
pml/templatetags/pml_inclusion_tags.pyc