Metadata-Version: 1.1
Name: django-pummel
Version: 0.0.8
Summary: Django PML template tags and utils (djang-pml was taken, okay!)
Home-page: http://github.com/praekelt/django-pummel
Author: Praekelt Foundation
Author-email: dev@praekeltfoundation.org
License: Proprietary
Platform: UNKNOWN
Classifier: Programming Language :: Python
Classifier: Development Status :: 4 - Beta
Classifier: Operating System :: OS Independent
Classifier: Framework :: Django
Classifier: Intended Audience :: Developers
Classifier: Topic :: Internet :: WWW/HTTP :: Dynamic Content
